{
  "cod": "029",
  "titulo": "Terreno 565,57 m²",
  "image": "/uploads/foto-terreno-langone.jpg",
  "tipo": "Terreno",
  "finalidade": "venda",
  "rural": false,
  "cidade": "Júlio de Castilhos",
  "endereco": "Rua Victor Langone",
  "preco": 68000,
  "dormitorios": 0,
  "caracteristicas": [
    "565,57 m² de área total",
    "Frente de 14,75 m",
    "Comprimento de 38,25 m"
  ],
  "descricao": "Terreno localizado na Rua Victor Langone.\n\nÁrea total de 565,57 m², com frente de 14,75 metros e comprimento de 38,25 metros.\n\nAgende sua visita!",
  "fotos": [
    {
      "foto": "/uploads/foto-terreno-langone.jpg"
    }
  ],
  "lat": -29.2334,
  "lng": -53.6901
}
